pepbench/__init__.py
pepbench/_docutils.py
pepbench/example_data.py
pepbench/algorithms/__init__.py
pepbench/algorithms/ecg.py
pepbench/algorithms/heartbeat_segmentation.py
pepbench/algorithms/icg.py
pepbench/algorithms/outlier_correction.py
pepbench/algorithms/preprocessing.py
pepbench/annotations/__init__.py
pepbench/annotations/_annotations.py
pepbench/annotations/stats.py
pepbench/data_handling/__init__.py
pepbench/data_handling/_data_handling.py
pepbench/data_handling/utils.py
pepbench/datasets/__init__.py
pepbench/datasets/_base_pep_extraction_dataset.py
pepbench/datasets/_example_dataset.py
pepbench/datasets/_helper.py
pepbench/datasets/empkins/__init__.py
pepbench/datasets/empkins/_dataset.py
pepbench/datasets/empkins/_helper.py
pepbench/datasets/guardian/__init__.py
pepbench/datasets/guardian/_dataset.py
pepbench/datasets/guardian/_helper.py
pepbench/datasets/guardian/_tfm_loader.py
pepbench/datasets/rebeat_icg/__init__.py
pepbench/datasets/rebeat_icg/_dataset.py
pepbench/datasets/rebeat_icg/_helper.py
pepbench/datasets/time_window_icg/__init__.py
pepbench/datasets/time_window_icg/_dataset.py
pepbench/datasets/time_window_icg/_helper.py
pepbench/evaluation/__init__.py
pepbench/evaluation/_error_metrics.py
pepbench/evaluation/_evaluation.py
pepbench/evaluation/_scoring.py
pepbench/evaluation/_scoring_aggregator.py
pepbench/export/__init__.py
pepbench/export/_latex.py
pepbench/heartbeat_matching/__init__.py
pepbench/heartbeat_matching/_heartbeat_matching.py
pepbench/io/__init__.py
pepbench/io/_io.py
pepbench/pipelines/__init__.py
pepbench/pipelines/_base_pipeline.py
pepbench/pipelines/_pipeline.py
pepbench/pipelines/_pipeline_reference_b_point.py
pepbench/pipelines/_pipeline_reference_q_peak.py
pepbench/plotting/__init__.py
pepbench/plotting/_base_plotting.py
pepbench/plotting/_utils.py
pepbench/plotting/algorithms.py
pepbench/plotting/results.py
pepbench/utils/__init__.py
pepbench/utils/_rename_maps.py
pepbench/utils/_timing.py
pepbench/utils/_types.py
pepbench-0.2.0.dist-info/METADATA
pepbench-0.2.0.dist-info/WHEEL
pepbench-0.2.0.dist-info/licenses/LICENSE
pepbench-0.2.0.dist-info/RECORD
