Metadata-Version: 2.4
Name: pepbench
Version: 0.2.0
Summary: A python package to benchmark different pre-ejection period (PEP) extraction algorithms.
Author-email: Robert Richer <robert.richer@fau.de>
License-Expression: MIT
License-File: LICENSE
Requires-Python: <4.0,>=3.10
Requires-Dist: biopsykit>=0.13.1
Requires-Dist: jinja2<4,>=3.1.4
Requires-Dist: pooch>=1.8.2
Requires-Dist: pywavelets>=1.8.0
Requires-Dist: tpcp>=2
